hardware/__init__.py
hardware/areca.py
hardware/bios_hp.py
hardware/cmdb.py
hardware/detect.py
hardware/detect_utils.py
hardware/diskinfo.py
hardware/generate.py
hardware/hpacucli.py
hardware/infiniband.py
hardware/ipmi.py
hardware/matcher.py
hardware/megacli.py
hardware/rtc.py
hardware/sensors.py
hardware/smart_utils.py
hardware/smart_utils_info.py
hardware/state.py
hardware/system.py
hardware/benchmark/__init__.py
hardware/benchmark/cpu.py
hardware/benchmark/disk.py
hardware/benchmark/mem.py
hardware/benchmark/utils.py
hardware/tests/__init__.py
hardware/tests/test_areca.py
hardware/tests/test_benchmark_cpu.py
hardware/tests/test_benchmark_disk.py
hardware/tests/test_benchmark_mem.py
hardware/tests/test_bios_hp.py
hardware/tests/test_cmdb.py
hardware/tests/test_detect_utils.py
hardware/tests/test_diskinfo.py
hardware/tests/test_ethtool.py
hardware/tests/test_generate.py
hardware/tests/test_hpacucli.py
hardware/tests/test_infiniband.py
hardware/tests/test_ipmi.py
hardware/tests/test_lldp.py
hardware/tests/test_matcher.py
hardware/tests/test_megacli.py
hardware/tests/test_smart_utils.py
hardware/tests/test_state.py
hardware/tests/test_system.py
hardware/tests/utils.py
hardware/tests/cardiff_samples/ProLiantBL460cGen8641016B21-HP-CZ3404YWNN9c-b6-54-88-2d-b0.hw_
hardware/tests/cardiff_samples/ProLiantBL460cGen8641016B21-HP-CZ3404YWNR9c-b6-54-88-5c-78.hw_
hardware/tests/cardiff_samples/ProLiantBL460cGen8641016B21-HP-CZ3404YWNT9c-b6-54-88-9c-48.hw_
hardware/tests/cardiff_samples/ProLiantBL460cGen8641016B21-HP-CZ3404YWNW9c-b6-54-88-9c-38.hw_
hardware/tests/cardiff_samples/ProLiantBL460cGen8641016B21-HP-CZ3404YWP29c-b6-54-88-9c-40.hw_
hardware/tests/cardiff_samples/ProLiantBL460cGen8641016B21-HP-CZ3404YWP49c-b6-54-88-cc-50.hw_
hardware/tests/cardiff_samples/ProLiantBL460cGen8641016B21-HP-CZ3404YWP69c-b6-54-88-1c-28.hw_
hardware/tests/cardiff_samples/ProLiantBL460cGen8641016B21-HP-CZ3404YWP89c-b6-54-88-7c-e0.hw_
hardware-0.32.0.dist-info/AUTHORS
hardware-0.32.0.dist-info/LICENSE
hardware-0.32.0.dist-info/METADATA
hardware-0.32.0.dist-info/WHEEL
hardware-0.32.0.dist-info/entry_points.txt
hardware-0.32.0.dist-info/pbr.json
hardware-0.32.0.dist-info/top_level.txt
hardware-0.32.0.dist-info/RECORD
