Metadata-Version: 2.1
Name: hardware
Version: 0.32.0
Summary: Hardware detection and classification utilities
Home-page: https://github.com/redhat-cip/hardware
Author: eNovance
Author-email: licensing@enovance.com
Classifier: Topic :: System :: Hardware
Classifier: Intended Audience :: Information Technology
Classifier: Intended Audience :: System Administrators
Classifier: License :: OSI Approved :: Apache Software License
Classifier: Operating System :: POSIX :: Linux
Classifier: Programming Language :: Python
Classifier: Programming Language :: Python :: 3
Classifier: Programming Language :: Python :: 3 :: Only
Classifier: Programming Language :: Python :: 3.8
Classifier: Programming Language :: Python :: 3.9
Classifier: Programming Language :: Python :: 3.10
Classifier: Programming Language :: Python :: 3.11
Classifier: Programming Language :: Python :: 3.12
Requires-Python: >=3.8
License-File: LICENSE
License-File: AUTHORS
Requires-Dist: pbr >=3.1.1
Requires-Dist: pexpect
